browsenextfile
